TpModel
