Metadata-Version: 1.0
Name: TpModel
Version: 0.3
Summary: TpModel
Home-page: UNKNOWN
Author: nbl
Author-email: UNKNOWN
License: UNKNOWN
Platform: UNKNOWN
